py_pyresult-1.0.0.dist-info/licenses/LICENSE
pyresult/__init__.py
pyresult/result.cp311-win_amd64.pyd
pyresult/result.py
pyresult/result__mypyc.cp311-win_amd64.pyd
py_pyresult-1.0.0.dist-info/METADATA
py_pyresult-1.0.0.dist-info/WHEEL
py_pyresult-1.0.0.dist-info/top_level.txt
py_pyresult-1.0.0.dist-info/RECORD
