Metadata-Version: 2.4
Name: py-pyresult
Version: 1.0.0
Summary: A high-performance, type-safe Result type for Python, inspired by Rust.
Author: imsf04
License: MIT
Project-URL: Homepage, https://github.com/imsf04/py-pyresult
Classifier: Programming Language :: Python :: 3
Classifier: License :: OSI Approved :: MIT License
Classifier: Operating System :: OS Independent
Classifier: Intended Audience :: Developers
Classifier: Topic :: Software Development :: Libraries :: Python Modules
Requires-Python: >=3.8
License-File: LICENSE
Dynamic: license-file
